dc_quantum_scheduling/__init__.py
dc_quantum_scheduling/client.py
dc_quantum_scheduling/io.py
dc_quantum_scheduling/models.py
dc_quantum_scheduling/processor.py
dc_quantum_scheduling/qiskit/__init__.py
dc_quantum_scheduling/qiskit/qiskit_provider.py
dc_quantum_scheduling/util.py
LICENSE
dc_quantum_scheduling-0.0.3.dist-info/LICENSE
dc_quantum_scheduling-0.0.3.dist-info/WHEEL
dc_quantum_scheduling-0.0.3.dist-info/METADATA
dc_quantum_scheduling-0.0.3.dist-info/RECORD
