Metadata-Version: 2.1
Name: dc-quantum-scheduling
Version: 0.0.3
Summary: 
Home-page: https://github.com/carstenblank/dc-quantum-scheduling
License: Apache Software License
Keywords: quantum,physics
Author: Carsten BLank
Author-email: blank@data-cybernetics.com
Requires-Python: >=3.7,<4
Classifier: Development Status :: 4 - Beta
Classifier: Environment :: Console
Classifier: Intended Audience :: Science/Research
Classifier: License :: OSI Approved :: Apache Software License
Classifier: License :: Other/Proprietary License
Classifier: Natural Language :: English
Classifier: Operating System :: MacOS :: MacOS X
Classifier: Operating System :: Microsoft :: Windows
Classifier: Operating System :: POSIX
Classifier: Operating System :: POSIX :: Linux
Classifier: Programming Language :: Python
Classifier: Programming Language :: Python :: 3
Classifier: Programming Language :: Python :: 3.7
Classifier: Programming Language :: Python :: 3.8
Classifier: Programming Language :: Python :: 3.9
Classifier: Programming Language :: Python :: 3.10
Classifier: Programming Language :: Python :: 3
Classifier: Programming Language :: Python :: 3 :: Only
Classifier: Programming Language :: Python :: 3.7
Classifier: Programming Language :: Python :: 3.8
Classifier: Programming Language :: Python :: 3.9
Classifier: Topic :: Scientific/Engineering :: Physics
Requires-Dist: pytz
Requires-Dist: qiskit
Requires-Dist: requests
Requires-Dist: retry
Project-URL: Repository, https://github.com/carstenblank/dc-quantum-scheduling
